hatch_ci/__init__.py
hatch_ci/_build.py
hatch_ci/_support.py
hatch_ci/build_hook.py
hatch_ci/cli.py
hatch_ci/code.py
hatch_ci/common.py
hatch_ci/exceptions.py
hatch_ci/fileos.py
hatch_ci/hooks.py
hatch_ci/scm.py
hatch_ci/script.py
hatch_ci/text.py
hatch_ci/tools.py
hatch_ci/version_hook.py
hatch_ci-0.1.3.dist-info/METADATA
hatch_ci-0.1.3.dist-info/WHEEL
hatch_ci-0.1.3.dist-info/entry_points.txt
hatch_ci-0.1.3.dist-info/licenses/LICENSE.txt
hatch_ci-0.1.3.dist-info/RECORD
