Metadata-Version: 2.3
Name: hatch-ci
Version: 0.1.3
Summary: Hatch plugin for ci system versioning
Project-URL: Issues, https://github.com/cav71/hatch-ci/issues
Project-URL: Source, https://github.com/cav71/hatch-ci
Author-email: Antonio Cavallo <a.cavallo@cavallinux.eu>
License: MIT
License-File: LICENSE.txt
Keywords: git,hatch,plugin,scm,version
Classifier: Development Status :: 4 - Beta
Classifier: Programming Language :: Python
Classifier: Programming Language :: Python :: 3.8
Classifier: Programming Language :: Python :: 3.9
Classifier: Programming Language :: Python :: 3.10
Classifier: Programming Language :: Python :: 3.11
Classifier: Programming Language :: Python :: 3.12
Classifier: Programming Language :: Python :: Implementation :: CPython
Classifier: Programming Language :: Python :: Implementation :: PyPy
Requires-Python: >=3.8
Requires-Dist: hatchling>=1.1.0
Requires-Dist: jinja2
Requires-Dist: typing-extensions
